league_utils/__init__.py
league_utils/entrypoint.py
league_utils/error.py
league_utils/monitor.py
league_utils/utils.py
league_utils/api/__init__.py
league_utils/api/championgg.py
league_utils/api/riot.py
league_utils/cli/__init__.py
league_utils/models/__init__.py
league_utils/models/item/__init__.py
league_utils/models/item/model.py
league_utils/models/item/stats.py
league_utils/models/item/tags.py
league_utils/models/item/worth.py
league_utils/models/itemset/__init__.py
league_utils/models/itemset/build.py
league_utils/models/itemset/constants.py
league_utils/models/itemset/model.py
league_utils/server/__init__.py
league_utils-1.0.5.dist-info/DESCRIPTION.rst
league_utils-1.0.5.dist-info/METADATA
league_utils-1.0.5.dist-info/RECORD
league_utils-1.0.5.dist-info/WHEEL
league_utils-1.0.5.dist-info/entry_points.txt
league_utils-1.0.5.dist-info/metadata.json
league_utils-1.0.5.dist-info/top_level.txt
tests/__init__.py
tests/test_cli.py
tests/test_error.py
tests/test_utils.py
