Metadata-Version: 2.0
Name: league-utils
Version: 1.0.5
Summary: League of Legends utilities, including an Item Set Generator
Home-page: https://github.com/TheKevJames/league.git
Author: Kevin James
Author-email: KevinJames@thekev.in
License: MIT License
Keywords: league legends game utilities item set generator efficiency isg
Platform: UNKNOWN
Classifier: Programming Language :: Python
Classifier: Programming Language :: Python :: 3 :: Only
Classifier: Development Status :: 5 - Production/Stable
Classifier: Natural Language :: English
Classifier: Intended Audience :: End Users/Desktop
Classifier: License :: OSI Approved :: MIT License
Requires-Dist: aiohttp
Requires-Dist: docopt
Requires-Dist: tqdm
